{
  "name": "Sean Larson",
  "age": 51,
  "address": {
    "street": "Edobew Pass",
    "city": "Mazuhu",
    "state": "MS",
    "zip": "08552"
  },
  "contact": {
    "phone": "(522) 872-7499",
    "servicePhone": "800739191"
  },
  "birthday": "1968-09-29T21:13:51.202Z",
  "ip": "23.140.97.230",
  "foo": "bar",
  "profile": {
    "about": "Nuso aco kidne gof lor arze selaufa wo gujibdoz so dan tivihi. Vacdi wejvam damojavo ebanoguv fit po ve foga tepuj una lezuwlaf gaj cowo vi. Zurzuv pabloz godci pave tah ecukikoz beugiric ra uhidega sa godse urropeta eza so doji esjini rines tupufcec.",
    "bio": "Co vozeno vicwen siwuc mo le atvukam levu bed wikod obizazi sunoav mogbo pure vo vuv. Zegopor rami uriguhi fam wisadvi woga inuva uve ispi wike nig rabauj zovos ke jelhibe dedo oprico. Vec fafguowe upenuf urwali nodmuati uruso uz zenub bac nejalug ujho zu pogoiwa igedolan."
  },
  "apiKey": "c872bc00fd1601feab6ae8acf100ab6589aa55a5a5fa83c5ea4cc60fc1e7fb33",
  "currency": {
    "code": "LSL",
    "name": "Lesotho Loti"
  }
}