{
  "name": "Janie Dean",
  "age": 41,
  "address": {
    "street": "Pomzet Circle",
    "city": "Ekhurhol",
    "state": "CT",
    "zip": "28563"
  },
  "contact": {
    "phone": "(988) 230-1834",
    "servicePhone": "800763486"
  },
  "birthday": "1989-01-14T14:57:11.605Z",
  "ip": "188.235.104.183",
  "foo": "bar",
  "profile": {
    "about": "Otpiz udagok bic ta zelig baghewbo tam we du ge la oka zapip cubbemib humalu viwtej. Duk miha jihpog pizomoup vobkotoj ver cubem ode kab bakva tubpiwi tipwujku ej ti. Nogsidzog rebefaz bato wap piseno mudim ka hoija menza mo cahje cunfeew. Onuob popivil bonupwof juuw am wowoh wezo it ri neorbu jiikul rez negkifur ruv.",
    "bio": "Jeb uco zimokoh non simru wuzmummu lidapgot hes ja bo zaoma lo etijuj vaz ci. Ced jihjalap momep kisuvu venuh cu jec bugwe hitmaula ugefofow sop onudas rug arodima jep. Jaud zejvugvu hagjen zoc mun huj kavwitur fusi eceohjo fecgir petamves ibadugoj zajhitguv anhem. Umigirad faufzo igu owe jad davohsap niuna tagsa utefe bipubzo bippeab giri embi edjaw for isusoim wekdo rakiuna."
  },
  "apiKey": "aabaf49eaf647ef9bd798eb21dc2a68f8162673eb76c71db65db14f336f42891",
  "currency": {
    "code": "PGK",
    "name": "Papua New Guinea Kina"
  }
}